bowler_py35-0.9.1.dist-info/dependency_links.txt
bowler_py35-0.9.1.dist-info/entry_points.txt
bowler_py35-0.9.1.dist-info/METADATA
bowler_py35-0.9.1.dist-info/top_level.txt
bowler_py35-0.9.1.dist-info/WHEEL
bowler/query.py
bowler/type_inference.py
bowler/helpers.py
bowler/imr.py
bowler/__main__.py
bowler/__init__.py
bowler/main.py
bowler/tool.py
bowler/types.py
bowler/tests/smoke.py
bowler/tests/query.py
bowler/tests/type_inference.py
bowler/tests/helpers.py
bowler/tests/__main__.py
bowler/tests/__init__.py
bowler/tests/tool.py
bowler/tests/lib.py
bowler/tests/smoke-target.py
bowler/README.md
bowler_py35-0.9.1.dist-info/LICENSE
bowler_py35-0.9.1.dist-info/RECORD