Metadata-Version: 2.1
Name: bowler-py35
Version: 0.9.1
Summary: Safe code refactoring for modern Python projects
Project-URL: Home, https://github.com/facebookincubator/bowler
Author: John Reese, Facebook
Author-email: jreese@fb.com
License: MIT
Requires-Python: >=3.5
Requires-Dist: attrs
Requires-Dist: click
Requires-Dist: fissix-py35
Requires-Dist: sh
